navv/__init__.py
navv/__main__.py
navv/_version.py
navv/bll.py
navv/commands.py
navv/data_types.py
navv/message_handler.py
navv/network_analysis.py
navv/spreadsheet_tools.py
navv/utilities.py
navv/validators.py
navv/zeek.py
navv/data/data.pkl
navv/data/mac-vendors.json
navv/gui/__init__.py
navv/gui/app.py
navv/gui/bll.py
navv/gui/utils.py
navv/gui/static/app.js
navv/gui/static/styles.css
navv/gui/static/css/bootstrap.min.css
navv/gui/static/css/bootstrap.min.css.map
navv/gui/static/css/bootstrap.rtl.min.css
navv/gui/static/css/bootstrap.rtl.min.css.map
navv/gui/static/img/navv-logo.png
navv/gui/static/js/bootstrap.bundle.min.js
navv/gui/static/js/bootstrap.bundle.min.js.map
navv/gui/templates/base.html
navv/gui/templates/create_new.html
navv/gui/templates/home.html
navv/gui/templates/update_existing.html
navv-3.3.5.dist-info/LICENSE
navv-3.3.5.dist-info/METADATA
navv-3.3.5.dist-info/NOTICE
navv-3.3.5.dist-info/WHEEL
navv-3.3.5.dist-info/entry_points.txt
navv-3.3.5.dist-info/top_level.txt
navv-3.3.5.dist-info/RECORD
