Metadata-Version: 2.1
Name: navv
Version: 3.3.5
Summary: Generate a spreadsheet for network traffic analysis from PCAP data and Zeek logs
Home-page: https://github.com/cisagov/network-architecture-verification-and-validation
Author: Seth Grover
Author-email: seth.grover@inl.gov
Project-URL: Bug Tracker, https://github.com/cisagov/network-architecture-verification-and-validation/issues
Classifier: Development Status :: 5 - Production/Stable
Classifier: Environment :: Console
Classifier: License :: OSI Approved :: BSD License
Classifier: Operating System :: OS Independent
Classifier: Programming Language :: Python :: 3
Classifier: Topic :: System :: Networking :: Monitoring
Classifier: Topic :: Utilities
Requires-Python: >=3.6
License-File: LICENSE
License-File: NOTICE
Requires-Dist: click >=8.1.6
Requires-Dist: flask >=2.3.2
Requires-Dist: lxml >=4.3.2
Requires-Dist: netaddr >=0.8.0
Requires-Dist: openpyxl >=3.1.2
Requires-Dist: pandas >=2.0.3
Requires-Dist: tqdm >=4.57.0
